Metadata-Version: 1.1
Name: git-pandas
Version: 1.2.0
Summary: A utility for interacting with data from git repositories as Pandas dataframes
Home-page: https://github.com/wdm0006/git-pandas
Author: Will McGinnis
Author-email: will@pedalwrencher.com
License: BSD
Download-URL: https://github.com/wdm0006/git-pandas/tarball/1.2.0
Keywords: git pandas data analysis
Platform: UNKNOWN
Classifier: Development Status :: 3 - Alpha
Classifier: Intended Audience :: Developers
Classifier: Programming Language :: Python :: 3
